first.py
test_audit_dog-0.0.1.dist-info/LICENCE.txt
test_audit_dog-0.0.1.dist-info/METADATA
test_audit_dog-0.0.1.dist-info/WHEEL
test_audit_dog-0.0.1.dist-info/entry_points.txt
test_audit_dog-0.0.1.dist-info/top_level.txt
test_audit_dog-0.0.1.dist-info/RECORD
