Metadata-Version: 2.1
Name: test-audit-dog
Version: 0.0.1
Summary: A small example package
License: UNKNOWN
Platform: UNKNOWN
License-File: LICENCE.txt
Requires-Dist: Click
Requires-Dist: pyDrive
Requires-Dist: requests
Requires-Dist: python-decouple
Requires-Dist: setuptools
Requires-Dist: pybtex
Requires-Dist: python-dotenv
